LICENSE
MANIFEST.in
README.md
requirements.txt
setup.py
usvisa/VERSION
usvisa/__init__.py
usvisa.egg-info/PKG-INFO
usvisa.egg-info/SOURCES.txt
usvisa.egg-info/dependency_links.txt
usvisa.egg-info/requires.txt
usvisa.egg-info/top_level.txt
usvisa/cloud_storage/__init__.py
usvisa/cloud_storage/aws_storage.py
usvisa/components/__init__.py
usvisa/components/data_01_ingestion.py
usvisa/components/data_02_validation.py
usvisa/components/data_03_transformation.py
usvisa/components/model_04_trainer.py
usvisa/components/model_05_validate.py
usvisa/components/model_06_pusher.py
usvisa/configuration/__init__.py
usvisa/configuration/aws_connection.py
usvisa/configuration/mongo_db_connection.py
usvisa/constants/__init__.py
usvisa/data_access/__init__.py
usvisa/data_access/usvisa_data.py
usvisa/entity/__init__.py
usvisa/entity/artifact_entity.py
usvisa/entity/config_entity.py
usvisa/entity/estimator.py
usvisa/entity/s3_estimator.py
usvisa/exception/__init__.py
usvisa/logger/__init__.py
usvisa/pipeline/__init__.py
usvisa/pipeline/prediction_pipeline.py
usvisa/pipeline/training_pipeline.py
usvisa/utils/__init__.py
usvisa/utils/main_utils.py