Metadata-Version: 2.1
Name: usvisa
Version: 1.0.3
Summary: Usvisa_prediction_model
Author: ashpaqueshaikh4236
Author-email: ashfaq664236@gmail.com
License: MIT
Classifier: License :: OSI Approved :: MIT License
Classifier: Programming Language :: Python
Classifier: Programming Language :: Python :: 3
Classifier: Programming Language :: Python :: 3.8
Classifier: Programming Language :: Python :: Implementation :: CPython
Classifier: Programming Language :: Python :: Implementation :: PyPy
Requires-Python: ==3.8.20
License-File: LICENSE
Requires-Dist: pandas
Requires-Dist: numpy
Requires-Dist: scipy
Requires-Dist: scikit-learn
Requires-Dist: imblearn
Requires-Dist: pymongo
Requires-Dist: evidently==0.2.8
Requires-Dist: dill
Requires-Dist: PyYAML
Requires-Dist: neuro_mf
Requires-Dist: boto3
Requires-Dist: mypy-boto3-s3
Requires-Dist: botocore
Requires-Dist: uvicorn
Requires-Dist: dvc
Requires-Dist: mlflow
Requires-Dist: flask-cors
Requires-Dist: Flask
